{
	"aboutUs": "关于我们",
	"company": "公司",
	"careers": "职业生涯",
	"our_brand": "我们的品牌",
	"for_studying": "为了学习",
	"blog": "博客",
	"roadmap": "路线图",
	"products": "产品",
	"cryptocommunity": "加密社区",
	"documentation": "文档",
	"terms_and_conditions": "条款和条件",
	"privacy_policy": "隐私政策",
	"cookie_policy": "Cookie 政策",
	"risk_warnings": "风险提示",
	"contact_us": "联系我们",
	"all_rights_reserved": "版权所有",
	"explore": "探索",
	"our_team": "我们的队伍",
	"use_logo": "标志的使用",
	"current_vacancy": "目前的职位空缺",
	"partnerships": "伙伴关系",
	"stay_up_latest_news": "随时了解最新消息",
	"sign_in": "登录",
	"sign_up": "注册",
	"ru": "俄语",
	"en": "英语",
	"uk": "乌克兰",
	"lv": "拉脱维亚语",
	"it": "意大利语"
}